starlet_setup/__init__.py
starlet_setup/__main__.py
starlet_setup/cli.py
starlet_setup/commands.py
starlet_setup/config.py
starlet_setup/interactive.py
starlet_setup/profiles.py
starlet_setup/repository.py
starlet_setup/utils.py
starlet_setup-1.2.0.dist-info/licenses/LICENSE
starlet_setup-1.2.0.dist-info/METADATA
starlet_setup-1.2.0.dist-info/WHEEL
starlet_setup-1.2.0.dist-info/entry_points.txt
starlet_setup-1.2.0.dist-info/top_level.txt
starlet_setup-1.2.0.dist-info/RECORD
