Metadata-Version: 2.4
Name: starlet-setup
Version: 1.2.0
Summary: Quick setup for CMake projects
Author-email: Mason L'Etoile <masonletoile@hotmail.com>
License: MIT
Project-URL: Homepage, https://github.com/masonlet/starlet-setup
Requires-Python: >=3.6
License-File: LICENSE
Provides-Extra: test
Requires-Dist: pytest>=7.0; extra == "test"
Dynamic: license-file
